int2str/__init__.py
int2str/int2str.py
int2str-0.1.0.dist-info/METADATA
int2str-0.1.0.dist-info/WHEEL
int2str-0.1.0.dist-info/top_level.txt
int2str-0.1.0.dist-info/RECORD
