Metadata-Version: 2.1
Name: int2str
Version: 0.1.0
Summary: Small int to words library
Home-page: https://int2str.readthedocs.io
Author: Jarlinton Zea
Author-email: jarlinton.zeastudio@outlook.com
License: MIT
